Workbook

Sheet detail - working
A1: Midyear capital requests and equipment ROI — supporting detail
A2: Department requests were copied from e-mails; approvals and expected in-service dates are incomplete. Source amounts reflect the current 6/30 company records.
A5: record | B5: date | C5: category | D5: dimension | E5: description | F5: source amount | G5: documented adjustment | H5: working amount | I5: status | J5: source / cutoff
A6: CX-26-017 | B6: 2026-06-30 | C6: Service | D6: Equipment line | E6: Three service vans; annual savings 54,000; 3.4 yr payback | F6: 186000 | G6: 0 | H6: =F6+G6 | I6: Approved - safety/reliability | J6: 2026-08-15
A7: CX-26-021 | B7: 2026-06-30 | C7: Fabrication | D7: TBD | E7: CNC pipe profiling machine; annual savings 86,000; 2.9 yr payback | F7: 248000 | G7: -248000 | H7: =F7+G7 | I7: Hold - electrical scope missing | J7: request log
A8: CX-26-024 | B8: 2026-06-30 | C8: Controls | D8: Cash | E8: Controls commissioning bench; annual savings 31,000; 3.0 yr payback | F8: 92000 | G8: 0 | H8: =F8+G8 | I8: Approved subject to training plan | J8: 2026-09-01
A9: CX-26-026 | B9: 2026-06-30 | C9: Operations | D9: TBD | E9: Warehouse racking expansion; annual savings 22,000; 7.6 yr payback | F9: 168000 | G9: -168000 | H9: =F9+G9 | I9: Deferred pending lease decision | J9: request log
A10: CX-26-029 | B10: 2026-06-30 | C10: IT / Operations | D10: Cash | E10: Field tablets - 24; annual savings 14,400; 2.7 yr payback | F10: 38400 | G10: 0 | H10: =F10+G10 | I10: Approved replacement cycle | J10: 2026-07-31

Sheet working summary
A1: Midyear capital requests and equipment ROI
A2: Owner-maintained finance workpaper | rev 5 | formula summary from detail
A5: category | B5: record count | C5: source total | D5: documented adj | E5: working total | F5: owner | G5: status | H5: interpretation
A6: Service | B6: =COUNTIF('detail - working'!C6:C10,A6) | C6: =SUMIF('detail - working'!C6:C10,A6,'detail - working'!F6:F10) | D6: =SUMIF('detail - working'!C6:C10,A6,'detail - working'!G6:G10) | E6: =C6+D6 | F6: NB | G6: review | H6: Documented timing/classification item; not an arbitrary plug
A7: Fabrication | B7: =COUNTIF('detail - working'!C6:C10,A7) | C7: =SUMIF('detail - working'!C6:C10,A7,'detail - working'!F6:F10) | D7: =SUMIF('detail - working'!C6:C10,A7,'detail - working'!G6:G10) | E7: =C7+D7 | F7: KS | G7: tied | H7: Formula-linked to full supporting detail
A8: Controls | B8: =COUNTIF('detail - working'!C6:C10,A8) | C8: =SUMIF('detail - working'!C6:C10,A8,'detail - working'!F6:F10) | D8: =SUMIF('detail - working'!C6:C10,A8,'detail - working'!G6:G10) | E8: =C8+D8 | F8: OL | G8: tied | H8: Formula-linked to full supporting detail
A9: Operations | B9: =COUNTIF('detail - working'!C6:C10,A9) | C9: =SUMIF('detail - working'!C6:C10,A9,'detail - working'!F6:F10) | D9: =SUMIF('detail - working'!C6:C10,A9,'detail - working'!G6:G10) | E9: =C9+D9 | F9: MW | G9: tied | H9: Formula-linked to full supporting detail
A10: IT / Operations | B10: =COUNTIF('detail - working'!C6:C10,A10) | C10: =SUMIF('detail - working'!C6:C10,A10,'detail - working'!F6:F10) | D10: =SUMIF('detail - working'!C6:C10,A10,'detail - working'!G6:G10) | E10: =C10+D10 | F10: MP | G10: tied | H10: Formula-linked to full supporting detail

Sheet links + lineage
A1: Workbook links and lineage
A2: External links are convenience references; imported source tabs and the 6/30 ERP cutoff remain the auditable basis.
A5: upstream source | B5: role | C5: cutoff/version | D5: link behavior | E5: current imported total | F5: control note
A6: 13wk cash_v9 - 6.26 roll - DCHO edits.xlsx | B6: primary upstream workbook/import | C6: 6/30/26 or named version | D6: Owner refreshes the imported source tab or scheduled query before close | E6: =SUM('detail - working'!H6:H10) | F6: Imported detail is retained so the workbook remains auditable without a live connection
A7: Vista ERP | B7: posted actuals | C7: 2026-06-30 | D7: scheduled report export | E7: =SUM('detail - working'!F6:F10) | F7: Authoritative for posted balances and transactions
A8: FY26 Op Plan_BoardApproved_12.18.25_FINAL2.xlsx | B8: plan | C8: approved 12/18/25 | D8: external workbook | E8: =0 | F8: Authoritative approved plan, not actuals
A9: WIP 5.31.26_FINAL_v7_revised NB.xlsx | B9: prior close | C9: 2026-05-31 | D9: external workbook | E9: =0 | F9: Prior-period baseline only
A10: manual owner evidence | B10: judgment / classification | C10: noted per row | D10: documented adjustment column | E10: =SUM('detail - working'!G6:G10) | F10: No silent plugs permitted

Sheet checks + signoff
A1: Midyear capital requests and equipment ROI — checks / sign-off
A2: Formula-driven arithmetic, population and lineage controls
A5: check | B5: expected | C5: actual / delta | D5: result | E5: explanation | F5: reviewer
A6: Detail arithmetic | B6: 0 | C6: =SUM('detail - working'!H6:H10)-SUM('detail - working'!F6:F10)-SUM('detail - working'!G6:G10) | D6: =IF(ABS(C6)<0.01,"PASS","FAIL") | E6: Working amount equals source plus documented adjustment
A7: Population count | B7: 5 | C7: =COUNTA('detail - working'!A6:A10) | D7: =IF(C7=B7,"PASS","FAIL") | E7: Full source population used for this workpaper
A8: Source lineage present | B8: 5 | C8: =COUNTA('detail - working'!J6:J10) | D8: =IF(C8=B8,"PASS","FAIL") | E8: Every row names a source/cutoff
A9: Silent adjustment check | B9: 0 | C9: =COUNTBLANK('detail - working'!G6:G10)-COUNTBLANK('detail - working'!A6:A10) | D9: =IF(C9=0,"PASS","FAIL") | E9: All adjustments are visible in column G
A10: Reviewer sign-off | B10: required | C10: pending | D10: =IF(C10=B10,"PASS","OPEN") | E10: Working file; sign-off remains open
