Workbook

Sheet Commercial Log
A1: Change Order and Claims Log
A2: Commercial status through 2026-06-30 17:00 PT | Executed changes are reflected in Vista ERP
A5: Project ID | B5: Reference | C5: Description | D5: Revenue Amount | E5: Estimated Cost | F5: Estimated Margin | G5: Status | H5: Last Updated | I5: Contract Included? | J5: Finance Review Status | K5: Support / Notes
A6: ARM-2417 | B6: PCO-017 | C6: OR congestion and after-hours premium | D6: 382000 | E6: 275000 | F6: =D6-E6 | G6: Submitted | H6: 46190 | I6: No | J6: Pending controller assessment under signed WIP policy | K6: Owner review; no executed directive
A7: ARM-2409 | B7: PCO-011 | C7: Freezer slab rework backcharge to concrete trade | D7: 185000 | E7: -185000 | F7: =D7-E7 | G7: Draft | H7: 46197 | I7: No | J7: Pending controller assessment under signed WIP policy | K7: Recovery disputed; no subcontractor acceptance
A8: ARM-2506 | B8: PCO-006 | C8: Chiller electrical service redesign | D8: 296000 | E8: 210000 | F8: =D8-E8 | G8: Pricing | H8: 46194 | I8: No | J8: Pending controller assessment under signed WIP policy | K8: Engineer-directed pricing only
A9: ARM-2514 | B9: CO-008 | C9: Gym ventilation scope revision | D9: 214000 | E9: 147000 | F9: =D9-E9 | G9: Approved | H9: 46185 | I9: Yes | J9: Executed before cutoff | K9: Executed bilateral change order
A10: ARM-2318 | B10: PCO-029 | C10: Final validation retest and extended support | D10: 68000 | E10: 45000 | F10: =D10-E10 | G10: Submitted | H10: 46200 | I10: No | J10: Pending controller assessment under signed WIP policy | K10: Customer disputes responsibility
A11: ARM-2605 | B11: PCO-002 | C11: Temporary ventilation for summer events | D11: 174000 | E11: 121000 | F11: =D11-E11 | G11: Under Review | H11: 46201 | I11: No | J11: Pending controller assessment under signed WIP policy | K11: Work not authorized at cutoff
A12: ARM-2403 | B12: CO-014 | C12: AHU-4 controls sequence revision | D12: 96000 | E12: 62000 | F12: =D12-E12 | G12: Approved | H12: 46161 | I12: Yes | J12: Executed before cutoff | K12: Executed
A13: ARM-2412 | B13: CO-009 | C13: Lab exhaust fan VFD replacements | D13: 133000 | E13: 88000 | F13: =D13-E13 | G13: Approved | H13: 46176 | I13: Yes | J13: Executed before cutoff | K13: Executed

Sheet Status Summary
A1: Commercial Pipeline Summary
A2: Unapproved amounts are pipeline only and do not alter WIP contract value
A5: Status | B5: Item Count | C5: Revenue Amount | D5: Estimated Cost
A6: Approved | B6: =COUNTIF('Commercial Log'!G$6:G$13,A6) | C6: =SUMIF('Commercial Log'!G$6:G$13,A6,'Commercial Log'!D$6:D$13) | D6: =SUMIF('Commercial Log'!G$6:G$13,A6,'Commercial Log'!E$6:E$13)
A7: Submitted | B7: =COUNTIF('Commercial Log'!G$6:G$13,A7) | C7: =SUMIF('Commercial Log'!G$6:G$13,A7,'Commercial Log'!D$6:D$13) | D7: =SUMIF('Commercial Log'!G$6:G$13,A7,'Commercial Log'!E$6:E$13)
A8: Under Review | B8: =COUNTIF('Commercial Log'!G$6:G$13,A8) | C8: =SUMIF('Commercial Log'!G$6:G$13,A8,'Commercial Log'!D$6:D$13) | D8: =SUMIF('Commercial Log'!G$6:G$13,A8,'Commercial Log'!E$6:E$13)
A9: Pricing | B9: =COUNTIF('Commercial Log'!G$6:G$13,A9) | C9: =SUMIF('Commercial Log'!G$6:G$13,A9,'Commercial Log'!D$6:D$13) | D9: =SUMIF('Commercial Log'!G$6:G$13,A9,'Commercial Log'!E$6:E$13)
A10: Draft | B10: =COUNTIF('Commercial Log'!G$6:G$13,A10) | C10: =SUMIF('Commercial Log'!G$6:G$13,A10,'Commercial Log'!D$6:D$13) | D10: =SUMIF('Commercial Log'!G$6:G$13,A10,'Commercial Log'!E$6:E$13)

Sheet Data Dictionary
A1: Commercial Log Data Dictionary
A2: Definitions used by Commercial, Project Accounting and WIP review
A5: Field | B5: Definition | C5: Owner | D5: Accounting Treatment
A6: Approved | B6: Executed bilateral change order or written directive meeting contract authorization requirements. | C6: Commercial Manager | D6: May be included in current contract value when recorded in Vista ERP.
A7: Submitted | B7: Formal pricing submitted; owner has not executed the change. | C7: Project Manager | D7: Do not recognize revenue solely from this status.
A8: Under Review | B8: Scope and commercial terms remain under owner/GC review. | C8: Commercial Manager | D8: Revenue excluded; evaluate unavoidable costs separately.
A9: Pricing | B9: Scope is being estimated or negotiated and is not yet a complete submission. | C9: Estimator / PM | D9: Revenue excluded; probable cost may require EAC treatment.
A10: Draft | B10: Internal position or claim theory not yet formally transmitted. | C10: Commercial Manager | D10: No revenue; recovery cannot reduce cost without persuasive support.
A11: Contract Included? | B11: Whether Vista ERP current contract value reflects the item at cutoff. | C11: Project Accounting | D11: Must reconcile to project contract report.
A12: Close Treatment | B12: Controller guidance for June estimate and recognition judgment. | C12: Controller | D12: Apply with source evidence and document any override.

Sheet PR working notes
A1: Priya's running commercial notes. Status values are informal; the Commercial Log and executed documents control.
A3: date typed | B3: job | C3: ref | D3: person | E3: note copied from call/e-mail | F3: next chase | G3: resolved?
A4: 2026-06-17 | B4: ARM-2417 | C4: PCO-017 | D4: PR | E4: Owner review; no executed directive | F4: 7/2 | G4: NO
A5: 6/12 | B5: ARM-2417 | C5: PCO-017 | D5: PR | E5: GC says pricing is with owner | F5: see above
A6: 2026-06-24 | B6: ARM-2409 | C6: PCO-011 | D6: MC | E6: Recovery disputed; no subcontractor acceptance | F6: 7/3 | G6: NO
A7: 6/13 | B7: ARM-2409 | C7: PCO-011 | D7: PR | E7: need executed page not meeting minutes | F7: see above
A8: 2026-06-21 | B8: ARM-2506 | C8: PCO-006 | D8: EM | E8: Engineer-directed pricing only | F8: 7/4 | G8: NO
A9: 6/14 | B9: ARM-2506 | C9: PCO-006 | D9: PR | E9: cost is moving before price | F9: see above
A10: 2026-06-12 | B10: ARM-2514 | C10: CO-008 | D10: LB | E10: Executed bilateral change order | F10: 7/5 | G10: maybe
A11: 6/15 | B11: ARM-2514 | C11: CO-008 | D11: PR | E11: PM assumed recovery - not accepted | F11: see above
A12: 2026-06-27 | B12: ARM-2318 | C12: PCO-029 | D12: PR | E12: Customer disputes responsibility | F12: 7/6 | G12: NO
A13: 6/16 | B13: ARM-2318 | C13: PCO-029 | D13: PR | E13: GC says pricing is with owner | F13: see above
A14: 2026-06-28 | B14: ARM-2605 | C14: PCO-002 | D14: MC | E14: Work not authorized at cutoff | F14: 7/7 | G14: NO
A15: 6/17 | B15: ARM-2605 | C15: PCO-002 | D15: PR | E15: need executed page not meeting minutes | F15: see above
A16: 2026-05-19 | B16: ARM-2403 | C16: CO-014 | D16: EM | E16: Executed | F16: 7/2 | G16: NO
A17: 6/18 | B17: ARM-2403 | C17: CO-014 | D17: PR | E17: cost is moving before price | F17: see above
A18: 2026-06-03 | B18: ARM-2412 | C18: CO-009 | D18: LB | E18: Executed | F18: 7/3 | G18: maybe
A19: 6/19 | B19: ARM-2412 | C19: CO-009 | D19: PR | E19: PM assumed recovery - not accepted | F19: see above

Sheet status xwalk old
A1: Old Procore-to-accounting status crosswalk. 'Directed' was removed from the current policy but is still present in historical exports.
A3: Ops status | B3: Commercial log status | C3: system contract? | D3: WIP revenue? | E3: cost treatment | F3: last policy review
A4: Potential | B4: Draft | C4: No | D4: No | E4: Assess probable cost | F4: 2024-11
A5: Pricing | B5: Pricing | C5: No | D5: No | E5: Assess probable cost | F5: 2024-11
A6: Submitted | B6: Submitted | C6: No | D6: No | E6: Include unavoidable cost | F6: 2024-11
A7: Directed | B7: Under Review | C7: Maybe | D7: NO - see policy | E7: Include probable cost | F7: 2023-06
A8: Approved | B8: Approved | C8: Yes after posting | D8: Yes after system update | E8: Include | F8: 2024-11
A9: Rejected | B9: Closed | C9: No | D9: No | E9: Recognize incurred cost | F9: 2024-11
