Workbook

Sheet Executive Summary
A1: FY2026 Annual Operating Plan
A2: Board approved 2025-12-18 | Base case | $000s except percentages
A4: FY26 Revenue | B4: =SUM('Monthly Plan'!B6:M6) | D4: Month | E4: Revenue | F4: Gross Profit | G4: Operating Income
A5: Gross Profit | B5: =SUM('Monthly Plan'!B8:M8) | D5: 2026-01 | E5: 3434266.7 | F5: 834526.8 | G5: 268526.8
A6: Gross Margin | B6: =B5/B4 | D6: 2026-02 | E6: 3514133.3 | F6: 867990.93 | G6: 301990.93
A7: Operating Expense | B7: =SUM('Monthly Plan'!B9:M9) | D7: 2026-03 | E7: 3753733.3 | F7: 949694.53 | G7: 341694.53
A8: Operating Income | B8: =SUM('Monthly Plan'!B10:M10) | D8: 2026-04 | E8: 3913466.7 | F8: 990107.07 | G8: 424107.07
A9: Operating Margin | B9: =B8/B4 | D9: 2026-05 | E9: 4153066.7 | F9: 1025807.5 | G9: 459807.47
D10: 2026-06 | E10: 4312800 | F10: 1065261.6 | G10: 499261.6
D11: 2026-07 | E11: 4432600 | F11: 1094852.2 | G11: 518664.2
D12: 2026-08 | E12: 4392666.7 | F12: 1084988.7 | G12: 466800.67
D13: 2026-09 | E13: 4193000 | F13: 1060829 | G13: 484641
D14: 2026-10 | E14: 4073200 | F14: 1030519.6 | G14: 454331.6
D15: 2026-11 | E15: 3913466.7 | F15: 966626.27 | G15: 390438.27
D16: 2026-12 | E16: 3833600 | F16: 931564.8 | G16: 355376.8

Sheet Monthly Plan
A1: FY2026 Monthly Plan
A2: Actual results should not be pasted into this approved budget tab
A5: P&L Line | B5: 2026-01 | C5: 2026-02 | D5: 2026-03 | E5: 2026-04 | F5: 2026-05 | G5: 2026-06 | H5: 2026-07 | I5: 2026-08 | J5: 2026-09 | K5: 2026-10 | L5: 2026-11 | M5: 2026-12 | N5: FY26
A6: Revenue | B6: 3434266.7 | C6: 3514133.3 | D6: 3753733.3 | E6: 3913466.7 | F6: 4153066.7 | G6: 4312800 | H6: 4432600 | I6: 4392666.7 | J6: 4193000 | K6: 4073200 | L6: 3913466.7 | M6: 3833600 | N6: =SUM(B6:M6)
A7: Cost of Revenue | B7: 2599739.9 | C7: 2646142.4 | D7: 2804038.8 | E7: 2923359.6 | F7: 3127259.2 | G7: 3247538.4 | H7: 3337747.8 | I7: 3307678 | J7: 3132171 | K7: 3042680.4 | L7: 2946840.4 | M7: 2902035.2 | N7: =SUM(B7:M7)
A8: Gross Profit | B8: 834526.8 | C8: 867990.93 | D8: 949694.53 | E8: 990107.07 | F8: 1025807.5 | G8: 1065261.6 | H8: 1094852.2 | I8: 1084988.7 | J8: 1060829 | K8: 1030519.6 | L8: 966626.27 | M8: 931564.8 | N8: =SUM(B8:M8)
A9: Operating Expense | B9: 566000 | C9: 566000 | D9: 608000 | E9: 566000 | F9: 566000 | G9: 566000 | H9: 576188 | I9: 618188 | J9: 576188 | K9: 576188 | L9: 576188 | M9: 576188 | N9: =SUM(B9:M9)
A10: Operating Income | B10: 268526.8 | C10: 301990.93 | D10: 341694.53 | E10: 424107.07 | F10: 459807.47 | G10: 499261.6 | H10: 518664.2 | I10: 466800.67 | J10: 484641 | K10: 454331.6 | L10: 390438.27 | M10: 355376.8 | N10: =SUM(B10:M10)

Sheet Department Plan
A1: FY2026 Department Plan
A2: Responsibility-center view | $000s
A5: Department | B5: Revenue | C5: Gross Profit | D5: Direct / Dept Opex | E5: Operating Contribution | F5: Primary FY26 Driver
A6: Construction - Portland | B6: 25876800 | C6: 5563512 | D6: 2160000 | E6: =C6-D6 | F6: Convert $38m opening backlog while containing field-overtime leakage
A7: Construction - Central Oregon | B7: 7667200 | C7: 1778790 | D7: 760000 | E7: =C7-D7 | F7: School and public-work backlog with summer labor concentration
A8: Service | B8: 8625600 | C8: 3407112 | D8: 2080000 | E8: =C8-D8 | F8: Maintenance agreement renewal and technician utilization
A9: Building Controls | B9: 5750400 | C9: 2098896 | D9: 1240000 | E9: =C9-D9 | F9: PDX controls execution and healthcare retrofit pipeline

Sheet Assumptions
A1: FY2026 Planning Assumptions
A2: Approved base-case drivers and policy constraints
A5: Driver | B5: Value | C5: Units | D5: Effective Period | E5: Owner | F5: Rationale / Source
A6: Construction backlog conversion | B6: 0.64 | C6: % of 2025-12-31 opening backlog | D6: FY2026 | E6: SVP Operations | F6: Project-by-project scheduling review dated 2025-11-21
A7: Field wage escalation | B7: 0.0475 | C7: % | D7: 2026-06 onward | E7: VP People | F7: Union agreements and market adjustment
A8: Material escalation | B8: 0.032 | C8: % | D8: FY2026 | E8: VP Operations | F8: Released buyout plus quoted commodity basket
A9: Service agreement retention | B9: 0.91 | C9: % | D9: FY2026 | E9: Service Director | F9: Cohort renewal analysis
A10: Service technician utilization | B10: 0.74 | C10: % paid hours | D10: FY2026 | E10: Service Director | F10: Trailing twelve months adjusted for hiring ramp
A11: DSO target | B11: 49 | C11: days | D11: FY2026 | E11: Controller | F11: Customer mix and contract terms
A12: Minimum operating liquidity | B12: 1250000 | C12: USD | D12: All weeks | E12: CFO | F12: Board treasury policy
A13: Revolver capacity | B13: 4000000 | C13: USD | D13: FY2026 | E13: CFO | F13: U.S. Bank facility amendment dated 2025-09-30

Sheet Checks
A1: AOP Model Checks
A2: Board-approved version controls
A5: Check | B5: Expected | C5: Actual / Delta | D5: Status | E5: Remediation
A6: Monthly gross profit formula | B6: 0 | C6: =ABS('Monthly Plan'!B8-('Monthly Plan'!B6-'Monthly Plan'!B7))+ABS('Monthly Plan'!C8-('Monthly Plan'!C6-'Monthly Plan'!C7))+ABS('Monthly Plan'!D8-('Monthly Plan'!D6-'Monthly Plan'!D7))+ABS('Monthly Plan'!E8-('Monthly Plan'!E6-'Monthly Plan'!E7))+ABS('Monthly Plan'!F8-('Monthly Plan'!F6-'Monthly Plan'!F7))+ABS('Monthly Plan'!G8-('Monthly Plan'!G6-'Monthly Plan'!G7))+ABS('Monthly Plan'!H8-('Monthly Plan'!H6-'Monthly Plan'!H7))+ABS('Monthly Plan'!I8-('Monthly Plan'!I6-'Monthly Plan'!I7))+ABS('Monthly Plan'!J8-('Monthly Plan'!J6-'Monthly Plan'!J7))+ABS('Monthly Plan'!K8-('Monthly Plan'!K6-'Monthly Plan'!K7))+ABS('Monthly Plan'!L8-('Monthly Plan'!L6-'Monthly Plan'!L7))+ABS('Monthly Plan'!M8-('Monthly Plan'!M6-'Monthly Plan'!M7)) | D6: =IF(ABS(C6)<0.01,"PASS","FAIL") | E6: Monthly Plan rows 6-8
A7: Monthly operating income formula | B7: 0 | C7: =ABS('Monthly Plan'!B10-('Monthly Plan'!B8-'Monthly Plan'!B9))+ABS('Monthly Plan'!C10-('Monthly Plan'!C8-'Monthly Plan'!C9))+ABS('Monthly Plan'!D10-('Monthly Plan'!D8-'Monthly Plan'!D9))+ABS('Monthly Plan'!E10-('Monthly Plan'!E8-'Monthly Plan'!E9))+ABS('Monthly Plan'!F10-('Monthly Plan'!F8-'Monthly Plan'!F9))+ABS('Monthly Plan'!G10-('Monthly Plan'!G8-'Monthly Plan'!G9))+ABS('Monthly Plan'!H10-('Monthly Plan'!H8-'Monthly Plan'!H9))+ABS('Monthly Plan'!I10-('Monthly Plan'!I8-'Monthly Plan'!I9))+ABS('Monthly Plan'!J10-('Monthly Plan'!J8-'Monthly Plan'!J9))+ABS('Monthly Plan'!K10-('Monthly Plan'!K8-'Monthly Plan'!K9))+ABS('Monthly Plan'!L10-('Monthly Plan'!L8-'Monthly Plan'!L9))+ABS('Monthly Plan'!M10-('Monthly Plan'!M8-'Monthly Plan'!M9)) | D7: =IF(ABS(C7)<0.01,"PASS","FAIL") | E7: Monthly Plan rows 8-10
A8: Department revenue ties to annual plan | B8: 0 | C8: =SUM('Department Plan'!B6:B9)-SUM('Monthly Plan'!B6:M6) | D8: =IF(ABS(C8)<1,"PASS","FAIL") | E8: Department Plan allocation
A9: Liquidity assumption populated | B9: 1250000 | C9: ='Assumptions'!B12 | D9: =IF(C9=B9,"PASS","FAIL") | E9: Assumptions row 12

Sheet backlog conv wkng
A1: 11/21/25 project review pasted from Ops. Contract values were not refreshed for December COs; approved plan adjustments are in columns H-J.
A3: Job | B3: Project | C3: 12/31 contract snapshot | D3: Est cost snapshot | E3: FY26 conversion % | F3: FY26 revenue calc | G3: PM | H3: manual adj | I3: reason | J3: review initials
A4: ARM-2318 | B4: Columbia Biologics Clean Utilities | C4: 9296500 | D4: 7271000 | E4: 0.42 | F4: =C4*E4+H4 | G4: Maya Chen | H4: 175000 | I4: schedule pull-forward per 12/9 call | J4: DC
A5: ARM-2403 | B5: Riverton Civic Center HVAC Renewal | C5: 6868000 | D5: 5109000 | E5: 0.5 | F5: =C5*E5+H5 | G5: Elliot Marks | H5: 0 | J5: MB
A6: ARM-2409 | B6: Northline Cold Storage Expansion | C6: 5526000 | D6: 4321000 | E6: 0.58 | F6: =C6*E6+H6 | G6: Priya Raman | H6: 0 | J6: MB
A7: ARM-2412 | B7: OSU Kelley Engineering Lab Ventilation | C7: 5411000 | D7: 4083000 | E7: 0.66 | F7: =C7*E7+H7 | G7: Elliot Marks | H7: 0 | J7: DC
A8: ARM-2417 | B8: Cascade Health Ambulatory Pavilion | C8: 10391000 | D8: 7970000 | E8: 0.74 | F8: =C8*E8+H8 | G8: Maya Chen | H8: 0 | J8: MB
A9: ARM-2421 | B9: Juniper Hotel Boiler Plant Replacement | C9: 2309000 | D9: 1755000 | E9: 0.82 | F9: =C9*E9+H9 | G9: Lucas Bennett | H9: 175000 | I9: schedule pull-forward per 12/9 call | J9: MB
A10: ARM-2501 | B10: PDX Concourse E Controls Retrofit | C10: 3688000 | D10: 2624000 | E10: 0.42 | F10: =C10*E10+H10 | G10: Sofia Alvarez | H10: 0 | J10: DC
A11: ARM-2506 | B11: Eastbank Data Hall Cooling Expansion | C11: 11580000 | D11: 8722000 | E11: 0.5 | F11: =C11*E11+H11 | G11: Priya Raman | H11: 0 | J11: MB
A12: ARM-2510 | B12: Hawthorne Yard Mixed-Use Mechanical | C12: 7740000 | D12: 5968000 | E12: 0.58 | F12: =C12*E12+H12 | G12: Maya Chen | H12: 0 | J12: MB
A13: ARM-2514 | B13: Redmond Unified Schools Phase 2 | C13: 7284000 | D13: 5529000 | E13: 0.66 | F13: =C13*E13+H13 | G13: Lucas Bennett | H13: 0 | J13: DC
A14: ARM-2518 | B14: Deschutes Fleet Services Maintenance Facility | C14: 3348000 | D14: 2523000 | E14: 0.74 | F14: =C14*E14+H14 | G14: Lucas Bennett | H14: 175000 | I14: schedule pull-forward per 12/9 call | J14: MB
A15: ARM-2522 | B15: Summit Surgical Center Central Plant | C15: 4585000 | D15: 3424000 | E15: 0.82 | F15: =C15*E15+H15 | G15: Elliot Marks | H15: 0 | J15: MB
A16: ARM-2526 | B16: Willamette Food Co-op Refrigeration Upgrade | C16: 1756500 | D16: 1370000 | E16: 0.42 | F16: =C16*E16+H16 | G16: Sofia Alvarez | H16: 0 | J16: DC
A17: ARM-2602 | B17: Pacific NW Distribution Center Heat Recovery | C17: 5920000 | D17: 4455000 | E17: 0.5 | F17: =C17*E17+H17 | G17: Priya Raman | H17: 0 | J17: MB
A18: ARM-2605 | B18: Rose Quarter Event Level Ventilation | C18: 6360000 | D18: 4782000 | E18: 0.58 | F18: =C18*E18+H18 | G18: Elliot Marks | H18: 0 | J18: MB
A19: ARM-2608 | B19: Cascade Health Imaging Suite Controls | C19: 1982000 | D19: 1396000 | E19: 0.66 | F19: =C19*E19+H19 | G19: Sofia Alvarez | H19: 175000 | I19: schedule pull-forward per 12/9 call | J19: DC

Sheet HC plan - old upload
A1: People upload received 11/14. Includes approved requisitions and three placeholders Finance later removed from the board plan.
A3: Dept | B3: Opening HC | C3: Jan | D3: Feb | E3: Mar | F3: Apr | G3: May | H3: Jun | I3: Jul | J3: Aug | K3: Sep | L3: Oct | M3: Nov | N3: Dec
A4: Construction Portland | B4: 58 | C4: 58 | D4: 59 | E4: 60 | F4: 61 | G4: 62 | H4: 63 | I4: 65 | J4: 65 | K4: 64 | L4: 64 | M4: 63 | N4: 63 | O4: 62
A5: Central Oregon | B5: 18 | C5: 18 | D5: 18 | E5: 19 | F5: 20 | G5: 21 | H5: 22 | I5: 23 | J5: 23 | K5: 23 | L5: 22 | M5: 22 | N5: 21 | O5: 21
A6: Service | B6: 19 | C6: 19 | D6: 20 | E6: 20 | F6: 21 | G6: 21 | H6: 22 | I6: 23 | J6: 24 | K6: 24 | L6: 25 | M6: 25 | N6: 25 | O6: 25
A7: Controls | B7: 9 | C7: 9 | D7: 9 | E7: 10 | F7: 10 | G7: 10 | H7: 11 | I7: 11 | J7: 11 | K7: 12 | L7: 12 | M7: 12 | N7: 12 | O7: 12
A8: Corporate | B8: 8 | C8: 8 | D8: 8 | E8: 8 | F8: 8 | G8: 8 | H8: 8 | I8: 8 | J8: 8 | K8: 8 | L8: 8 | M8: 8 | N8: 8 | O8: 8
A9: PLACEHOLDER - acquisitions | B9: 0 | C9: 0 | D9: 0 | E9: 0 | F9: 0 | G9: 0 | H9: 0 | I9: 3 | J9: 3 | K9: 3 | L9: 3 | M9: 3 | N9: 3 | O9: 3

Sheet v log + loose notes
A1: This tab was not updated for every save. File modified timestamp and Board packet control if they disagree.
A3: version typed | B3: date | C3: by | D3: what changed | E3: board? | F3: loose note
A4: v14 | B4: 12/10/25 | C4: MB | D4: Service retention and labor rates | E4: No | F4: DC wants downside case but not in board tabs
A5: v15 | B5: 12/16/25 | C5: MB | D5: Backlog project-by-project refresh | E5: Draft | F5: three jobs manually overridden
A6: FINAL | B6: 12/18/25 | C6: DC | D6: Board package | E6: YES | F6: capex slide differs by $92k timing only
A7: FINAL2 | B7: 12/19/25 | C7: MB | D7: fixed typo in source note--no plan change | E7: same numbers | F7: saved after meeting

Sheet Source Log
A1: FY26 AOP Source Log
A2: Recurring workpaper metadata and refresh lineage
A4: Item | B4: Period / As-of | C4: Source Type | D4: Source Name | E4: Reference | F4: Owner | G4: Refresh Date | H4: Status | I4: Notes
A5: Opening backlog | B5: 2025-12-31 | C5: Accounting report | D5: Backlog by Project | E5: JC-610 | F5: SVP Operations | G5: 45982 | H5: Current | I5: Reviewed job by job
A6: Labor rates | B6: FY2026 | C6: HR / union schedules | D6: Field Compensation Planning Extract | E6: People/Comp/FY26 | F6: VP People | G6: 45975 | H6: Current | I6: Loaded wage and burden assumptions
A7: Liquidity policy | B7: FY2026 | C7: Board policy | D7: Treasury and Liquidity Policy | E7: Board/2025-12-18 | F7: CFO | G7: 46009 | H7: Current | I7: $1.25m weekly floor
